{
    "code": "A00000",
    "msg": "获取信息成功",
    "data": {
        "total": 101,
        "pageSize": 1,        
        "pageNo": 0,
        "result": [
                {
                    "Src" : "css-src/slider/images/picture-0.jpg",
                    "Name": "月季",
                    "Info":"等待有希望的希望，幸福、光荣、美艳长新。"
                }, {
                    "Src" : "css-src/slider/images/picture-1.jpg",
                    "Name": "茉莉花",
                    "Info":"表示爱情和友谊。"
                }, {
                    "Src" : "css-src/slider/images/picture-2.jpg",
                    "Name": "梅花",
                    "Info":"凌霜斗雪，迎春开放，风骨俊傲，不趋荣利。"
                }, {
                    "Src" : "css-src/slider/images/picture-3.jpg",
                    "Name": "栀子花",
                    "Info":"永恒的爱与约定,很美的寄托。"
                }, {
                    "Src" : "css-src/slider/images/picture-4.jpg",
                    "Name": "风信子",
                    "Info":"得到我的爱，你一定会幸福快乐。"
                }, {
                    "Src" : "css-src/slider/images/picture-5.jpg",
                    "Name": "紫罗兰",
                    "Info":"永恒的美；质朴，美德。"
                }, {
                    "Src" : "css-src/slider/images/picture-6.jpg",
                    "Name": "桃花",
                    "Info":"爱情的俘虏。"
                }, {
                    "Src" : "css-src/slider/images/picture-7.jpg",
                    "Name": "桔梗",
                    "Info":"永恒不变的爱。"
                }, {
                    "Src" : "css-src/slider/images/picture-8.jpg",
                    "Name": "桂花",
                    "Info":"吸入你的气息。"
                }, {
                    "Src" : "css-src/slider/images/picture-9.jpg",
                    "Name": "杜鹃花",
                    "Info":"永远属于你。"
                }
            ]
        }
}